README.txt
setup.cfg
setup.py
ext_time/__init__.py
ext_time/ext_time.py
ext_time/tool.py
ext_time.egg-info/PKG-INFO
ext_time.egg-info/SOURCES.txt
ext_time.egg-info/dependency_links.txt
ext_time.egg-info/top_level.txt